__init__.py
v1/__init__.py
v1/client.py
v2/__init__.py
v2/client.py
agntcy_dir_client_sdk-0.1.0.dist-info/METADATA
agntcy_dir_client_sdk-0.1.0.dist-info/WHEEL
agntcy_dir_client_sdk-0.1.0.dist-info/top_level.txt
agntcy_dir_client_sdk-0.1.0.dist-info/RECORD
