Metadata-Version: 2.4
Name: agntcy-dir-client-sdk
Version: 0.1.0
Summary: Directory client SDK
Requires-Python: >=3.13.2
Requires-Dist: agntcy-dir-grpc-python==1.73.1.1.20250714095524+83e094ab3172
